setup.py
PyDSI.egg-info/PKG-INFO
PyDSI.egg-info/SOURCES.txt
PyDSI.egg-info/dependency_links.txt
PyDSI.egg-info/not-zip-safe
PyDSI.egg-info/top_level.txt
pydsi/__init__.py
pydsi/methods.py
pydsi/outputfiles.py
pydsi.egg-info/PKG-INFO
pydsi.egg-info/SOURCES.txt
pydsi.egg-info/dependency_links.txt
pydsi.egg-info/not-zip-safe
pydsi.egg-info/top_level.txt