Metadata-Version: 1.0
Name: pydsi
Version: 0.1.3
Summary: Statistical variational inference for dynamical systems.
Home-page: http://github.com/joetaylor94/pydsi
Author: Joseph D. Taylor
Author-email: j.taylor@bath.ac.uk
License: MIT
Keywords: variational data assimilation chaos dynamical systems nonlinear
Platform: UNKNOWN
